easyjwt/__init__.py
easyjwt/easyjwt.py
easyjwt/enums.py
easyjwt/errors.py
easyjwt/restoration.py
easyjwt-0.2.1.dist-info/LICENSE
easyjwt-0.2.1.dist-info/METADATA
easyjwt-0.2.1.dist-info/WHEEL
easyjwt-0.2.1.dist-info/top_level.txt
easyjwt-0.2.1.dist-info/RECORD
