Metadata-Version: 2.1
Name: easyjwt
Version: 0.2.1
Summary: Super simple JSON Web Tokens with Python
Home-page: https://github.com/BMeu/EasyJWT
Author: Bastian Meyer
Author-email: bastian@bastianmeyer.eu
License: UNKNOWN
Project-URL: Documentation, https://easyjwt.readthedocs.io/en/latest/?badge=latest
Project-URL: Source, https://github.com/BMeu/EasyJWT
Project-URL: Tracker, https://github.com/BMeu/EasyJWT/issues
Keywords: jwt token tokens JSON
Platform: UNKNOWN
Classifier: Development Status :: 4 - Beta
Classifier: Intended Audience :: Developers
Classifier: License :: OSI Approved :: MIT License
Classifier: Programming Language :: Python :: 3
Classifier: Programming Language :: Python :: 3.6
Classifier: Programming Language :: Python :: 3.7
Classifier: Programming Language :: Python :: 3.8
Classifier: Programming Language :: Python :: 3.9
Requires-Python: >=3.6
Requires-Dist: bidict (==0.21.*)
Requires-Dist: PyJWT (==2.0.*)
